email_auth/__init__.py
email_auth/models.py
email_auth/migrations/0001_initial.py
email_auth/migrations/0002_auto_20160327_1119.py
email_auth/migrations/0003_django110.py
email_auth/migrations/0004_auto_20170411_1733.py
email_auth/migrations/0005_auto_20191123_2051.py
email_auth/migrations/__init__.py
shop/__init__.py
shop/apps.py
shop/cms_apphooks.py
shop/cms_menus.py
shop/conf.py
shop/context_processors.py
shop/deferred.py
shop/exceptions.py
shop/filters.py
shop/messages.py
shop/middleware.py
shop/patches.py
shop/sekizai_processors.py
shop/signals.py
shop/transition.py
shop/admin/__init__.py
shop/admin/customer.py
shop/admin/delivery.py
shop/admin/notification.py
shop/admin/order.py
shop/admin/product.py
shop/admin/defaults/__init__.py
shop/admin/defaults/commodity.py
shop/admin/defaults/customer.py
shop/admin/defaults/order.py
shop/cascade/__init__.py
shop/cascade/auth.py
shop/cascade/breadcrumb.py
shop/cascade/cart.py
shop/cascade/catalog.py
shop/cascade/checkout.py
shop/cascade/extensions.py
shop/cascade/order.py
shop/cascade/plugin_base.py
shop/cascade/processbar.py
shop/cascade/search.py
shop/cascade/segmentation.py
shop/cascade/settings.py
shop/forms/__init__.py
shop/forms/auth.py
shop/forms/base.py
shop/forms/checkout.py
shop/forms/widgets.py
shop/forms/wizards.py
shop/locale/da/LC_MESSAGES/django.mo
shop/locale/da/LC_MESSAGES/django.po
shop/locale/de/LC_MESSAGES/django.mo
shop/locale/de/LC_MESSAGES/django.po
shop/locale/en/LC_MESSAGES/django.mo
shop/locale/en/LC_MESSAGES/django.po
shop/locale/es/LC_MESSAGES/django.mo
shop/locale/es/LC_MESSAGES/django.po
shop/locale/fr/LC_MESSAGES/django.mo
shop/locale/fr/LC_MESSAGES/django.po
shop/locale/hr/LC_MESSAGES/django.mo
shop/locale/hr/LC_MESSAGES/django.po
shop/locale/it/LC_MESSAGES/django.mo
shop/locale/it/LC_MESSAGES/django.po
shop/locale/ja/LC_MESSAGES/django.mo
shop/locale/ja/LC_MESSAGES/django.po
shop/locale/ko/LC_MESSAGES/django.mo
shop/locale/ko/LC_MESSAGES/django.po
shop/locale/nl/LC_MESSAGES/django.mo
django_shop-1.2.4.dist-info/LICENSE.txt
django_shop-1.2.4.dist-info/METADATA
django_shop-1.2.4.dist-info/WHEEL
django_shop-1.2.4.dist-info/top_level.txt
django_shop-1.2.4.dist-info/RECORD
